<?xml version="1.0"?>
<sommaire>
    <bouton>
        <titre> Accueil </titre>
        <lien> ./index.html </lien>
    </bouton>

    <bouton lot="commandement">
        <titre> Les 10 commandements </titre>
        <lien> ./dix_commandements.html</lien>

            <!-- ### # ### -->
            <sousbouton>
                <titre> sur Dieu </titre>
                <lien> dix_commandements.html#1 </lien>
            </sousbouton>

            <!-- ### # ### -->
            <sousbouton>
                <titre> sur les parents </titre>
                <lien> dix_commandements.html#2 </lien>
            </sousbouton>

            <!-- ### # ### -->
            <sousbouton>
                <titre> sur la vie </titre>
                <lien> dix_commandements.html#3 </lien>
            </sousbouton>

            <!-- ### # ### -->
            <sousbouton>
                <titre> sur l'adultère </titre>
                <lien> dix_commandements.html#4 </lien>
            </sousbouton>

            <!-- ### # ### -->
            <sousbouton>
                <titre> sur l'adultère </titre>
                <lien> dix_commandements.html#5 </lien>
            </sousbouton>

            <!-- ### # ### -->
            <sousbouton>
                <titre> sur le témoignage </titre>
                <lien> dix_commandements.html#6 </lien>
            </sousbouton>

            <!-- ### # ### -->
            <sousbouton>
                <titre> sur la jalousie </titre>
                <lien> dix_commandements.html#7 </lien>
            </sousbouton>

    </bouton>

    <bouton lot="montagne">
        <titre> Sermon de la montagne </titre>
        <lien> ./montagne.html </lien>

        <!-- ### # ### -->
        <sousbouton>
            <titre> Rapport à la loi </titre>
            <lien> montagne.html#1 </lien>
        </sousbouton>

        <!-- ### # ### -->
        <sousbouton>
            <titre> Sur les dix commandements </titre>
            <lien> montagne.html#2 </lien>
        </sousbouton>

        <!-- ### # ### -->
        <sousbouton>
            <titre> De la sincérité </titre>
            <lien> montagne.html#3 </lien>
        </sousbouton>

        <!-- ### # ### -->
        <sousbouton>
            <titre> Le Notre-Père </titre>
            <lien> montagne.html#4 </lien>
        </sousbouton>

        <!-- ### # ### -->
        <sousbouton>
            <titre> La passion pour les richesses </titre>
            <lien> montagne.html#5 </lien>
        </sousbouton>

        <!-- ### # ### -->
        <sousbouton>
            <titre> Dieu prendra soin de vous </titre>
            <lien> montagne.html#6 </lien>
        </sousbouton>

        <!-- ### # ### -->
        <sousbouton>
            <titre> À chaque jour suffit sa peine </titre>
            <lien> montagne.html#7 </lien>
        </sousbouton>

        <!-- ### # ### -->
        <sousbouton>
            <titre> La poutre </titre>
            <lien> montagne.html#8 </lien>
        </sousbouton>

        <!-- ### # ### -->
        <sousbouton>
            <titre> De la prière </titre>
            <lien> montagne.html#9 </lien>
        </sousbouton>

        <!-- ### # ### -->
        <sousbouton>
            <titre> Les faux prophètes </titre>
            <lien> montagne.html#10 </lien>
        </sousbouton>

        <!-- ### # ### -->
        <sousbouton>
            <titre> De la foi et du salut </titre>
            <lien> montagne.html#11 </lien>
        </sousbouton>
    </bouton>

    <bouton>
        <titre> Pour aller plus loin </titre>
        <lien> ./plus_loin.html </lien>
    </bouton>

<!-- ### # ### -->

</sommaire>
